{
  "variants": {
    "face=floor,facing=north": {
      "model": "happyholidays:block/gold_christmas_bells",
      "y": 180
    },
    "face=wall,facing=north": {
      "model": "happyholidays:block/gold_christmas_bells_side",
      "y": 180
    },
    "face=ceiling,facing=north": {
      "model": "happyholidays:block/gold_christmas_bells_hanging",
      "y": 180
    },
    "face=floor,facing=south": {
      "model": "happyholidays:block/gold_christmas_bells"
    },
    "face=wall,facing=south": {
      "model": "happyholidays:block/gold_christmas_bells_side"
    },
    "face=ceiling,facing=south": {
      "model": "happyholidays:block/gold_christmas_bells_hanging"
    },
    "face=floor,facing=west": {
      "model": "happyholidays:block/gold_christmas_bells",
      "y": 90
    },
    "face=wall,facing=west": {
      "model": "happyholidays:block/gold_christmas_bells_side",
      "y": 90
    },
    "face=ceiling,facing=west": {
      "model": "happyholidays:block/gold_christmas_bells_hanging",
      "y": 90
    },
    "face=floor,facing=east": {
      "model": "happyholidays:block/gold_christmas_bells",
      "y": 270
    },
    "face=wall,facing=east": {
      "model": "happyholidays:block/gold_christmas_bells_side",
      "y": 270
    },
    "face=ceiling,facing=east": {
      "model": "happyholidays:block/gold_christmas_bells_hanging",
      "y": 270
    }
  }
}